{"status":"ok","totalResults":66,"articles":[{"source":{"id":null,"name":"Calcalist.co.il"},"author":null,"title":"אפל ניפצה את תחזיות הרווח וההכנסות לרבעון - כלכליסט","description":"ענקית הטכנולוגיה רשמה רווח נקי מתואם של 2.1 דולרים למניה על הכנסות שיא של 123.9 מיליארד דולר. ההכנסות ממכירת אייפונים עלו ב-9.2%, וממכירת מחשבי מק - ב-25.1%; המניה מזנקת ביותר מ-3% במסחר המאוחר","url":"https://www.calcalist.co.il/market/article/skgsguxrt","urlToImage":"https://images1.calcalist.co.il/picserver3/crop_images/2021/02/24/1062117/1062117_338_39_622_350_0_large.jpg","publishedAt":"2022-01-27T21:33:55Z","content":"( ) - . 123.9 - 11.2% , . -20.4% -34.63 , -2.1 . \r\n, 71.63 , 9.2% 67.7 . , , -23.8% -19.52 . , , 13.3% -14.7 . -25.1% -10.85 , 14.1% -7.25 .\r\n, 21% , -25.8 . -11.2% -51.5 , -8.9% -29.75 - -19.3% -9.8… [+91 chars]"},{"source":{"id":"google-news","name":"Google News"},"author":null,"title":"שאומי: אלה המכשירים הראשונים שיעודכנו ל-MIUI 13 - TGspot.co.il","description":null,"url":"https://news.google.com/__i/rss/rd/articles/CBMiS2h0dHBzOi8vd3d3LnRnc3BvdC5jby5pbC94aWFvbWktc2hhcmVzLWl0cy1taXVpLTEzLWdsb2JhbC1yb2xsb3V0LXNjaGVkdWxlL9IBAA?oc=5","urlToImage":null,"publishedAt":"2022-01-27T19:33:49Z","content":null},{"source":{"id":null,"name":"Ice.co.il"},"author":"יאיר מור","title":"וואטסאפ מסתבכת: זה האולטימטום המדאיג שקיבלה - אייס","description":"<p>אפליקציית התקשורת הפופולארית בעולם עלולה למצוא את עצמה בקרוב תחת סנקציות שונות, לאחר שהוטל עליה לעשות באופן רטרואקטיבי את מה שהיא מנסה להימנע ממנו כבר שנה שלמה</p>","url":"http://www.ice.co.il/digital-140/news/article/842154","urlToImage":"https://img.ice.co.il/giflib/news/13ice09122021.jpg","publishedAt":"2022-01-27T19:21:00Z","content":"( flickr)\r\n, , , , . , , , ( ). , . , , ."},{"source":{"id":null,"name":"Ice.co.il"},"author":"יאיר מור","title":"מיקרוסופט מזעזעת את העולם: לא צריך יותר סמארטפון במשרד - אייס","description":"ענקית התוכנה הפתיעה והכריזה על עדכון ענק למחשבים, שיאפשר להם לעשות את כל מה שאנשים רגילים לעשות בסמארטפונים שלהם","url":"http://www.ice.co.il/digital-140/news/article/842104","urlToImage":"https://img.ice.co.il/giflib/news/6ice29122021.jpg","publishedAt":"2022-01-27T17:04:00Z","content":"( unsplash)\r\n, : , , , ; , , , ; , , ; , \" , , , AMD ARM.\r\n( ), ( -Microsoft Teams, ), ( ) ' , Windows 10 \"\" -Windows 11, ."},{"source":{"id":"ynet","name":"Ynet"},"author":"לירן לוי","title":"ברמת האיום הגבוהה ביותר: אבטחה צמודה לשוטרים מפרשת אהוביה סנדק - ynet.co.il","description":"אחרי ההודעה על סגירת התיק נגד ארבעת השוטרים, שהיו מעורבים במרדף שהסתיים במות הנער בן ה-16, נודע כי הם מוגדרים מאוימים ברמה הגבוה ביותר, וזוכים לאבטחה צמודה ולסיורים תכופים של ניידות ליד בתיהם. פורסמה שיחת טלפון שהגיעה למשטרה לפני התקרית: \"זרקו אבנים ומיד נכנס…","url":"https://www.ynet.co.il/news/article/skvuorgry","urlToImage":"https://ynet-images1.yit.co.il/picserver5/crop_images/2020/12/21/BytMySA2v/BytMySA2v_1_0_640_360_0_large.jpg","publishedAt":"2022-01-27T16:35:56Z","content":", - . , 2020, \" , . -16 . \r\n\" (\"\") \", , . \" \". - - . \" \" , \".\r\n, . \" \" , \", \". \" . , , . \r\n\" , , , . , , . , , , , , \". \r\n\": \" , - , , . , - , . , . , \", , \", .\r\n. \" , \", . \" \" \" , , , , . , \" \" \". \r… [+31 chars]"},{"source":{"id":"ynet","name":"Ynet"},"author":"אודי עציון","title":"בתוך 7 חודשים: תע\"א תכשיר חסרי ניסיון להנדסת תוכנה דרך חברה חיצונית - ynet.co.il","description":"בגלל המחסור בעובדים בתחום, תקלוט התעשייה האווירית בוגרי מדעים מדויקים שיוכשרו כאנשי תוכנה בקורס אינטנסיבי בן 10 שעות ביום. יועסקו בשנתיים הראשונות באמצעות אינפיניטי, ועלות ההכשרה, כ-100 אלף שקל, תקוזז משכרם","url":"https://www.ynet.co.il/economy/article/ry6iprx0y","urlToImage":"https://ynet-images1.yit.co.il/picserver5/crop_images/2020/05/09/SJOySgV9L/SJOySgV9L_0_0_640_360_0_large.jpg","publishedAt":"2022-01-27T16:32:17Z","content":", . , , . -100 , \" , . 24 \".\r\n\" -100 , 2 \", , . \" . , , \".\r\n, -30 , - . \" \", , \", , \" R&amp;D. \" , \", \"."},{"source":{"id":null,"name":"Geektime.co.il"},"author":"אושרי אלקסלסי","title":"סטארטאפ ישראלי נעזר בסאונד ו-AI כדי לשמור מרחוק על קשישים - גיקטיים","description":"הסטארטאפ הישראלי Sensi.ai פיתח מערכת לניטור מטופלים סיעודיים מבוססת קול; המנכ''לית מספרת לנו שסבב הגיוס הושלם תוך חודשיים בלבד","url":"https://www.geektime.co.il/sensi-ai-raises-14m-in-a-round-to-monitor-the-elderly-without-cameras/","urlToImage":"https://files.geektime.co.il/wp-content/uploads/2022/01/georg-arthur-pflueger-TeWwYARfcM4-unsplash-1643289841-600x315.jpg","publishedAt":"2022-01-27T16:26:10Z","content":"Sensi.ai ; ” \r\n: + | : \r\n. , . .  -Age-Tech Sensi.ai, , (’) A 14 . Entrée Capital , Flint Capital -Homeward Ventures, : Almeda Ventures, Operator Partners, Jibe Ventures (Google Health AI).\r\n“ , ”\r\nS… [+307 chars]"},{"source":{"id":null,"name":"Haaretz.co.il"},"author":"איתן לשם","title":"AirTag של אפל סייעה לחשוף סוכנות ביון גרמנית חשאית - הארץ","description":"מכשירי האיתור של אפל כבר הפכו מזמן לכלי מעקב, וכעת הצליחה חוקרת גרמנייה להוכיח את קיומה של סוכנות המשמשת כיסוי לפעילות מודיעין בתוך גרמניה – על אף הכחשות הממשלה – בעזרת משלוח שהכיל דיסקית כזו","url":"https://www.haaretz.co.il/captain/net/.premium-1.10571760","urlToImage":"https://www.haaretz.co.il/polopoly_fs/1.10571787.1643300552!/image/1045473740.jpg_gen/derivatives/headline_1200x630/1045473740.jpg?wtm=1.10571787","publishedAt":"2022-01-27T16:13:00Z","content":"AirTag . ' , , . , . 800 , , \" \" \" \".\r\n...\r\n<ol><li></li></ol><ol><li></li></ol><ol></ol>"},{"source":{"id":null,"name":"Calcalist.co.il"},"author":null,"title":"מדענים: פריצת דרך לקראת הפיכת היתוך גרעיני לאנרגיה - כלכליסט","description":"בעזרת הלייזר הגדול בעולם, מדענים גרמו לראשונה לדלק ההיתוך לחמם עצמו מעבר לחום שהחדירו לו. בניגוד לשריפת דלקים מאובנים, היתוך מאפשר יצירת אנרגיה מרובה בלי זיהום, פסולת רדיואקטיבית או פליטת גזי חממה","url":"https://www.calcalist.co.il/world_news/article/rjy63xl0y","urlToImage":"https://images1.calcalist.co.il/picserver3/crop_images/2022/01/27/SyMjiJx0t/SyMjiJx0t_0_0_3000_1689_0_large.jpg","publishedAt":"2022-01-27T14:17:37Z","content":"192 -2 \" . . \" , \", . \" , \", . , . \" \", . \r\nwindow._taboola = window._taboola || [];\r\n _taboola.push({flush: true});"},{"source":{"id":null,"name":"Themarker.com"},"author":"סימי ספולטר","title":"ונטי הישראלית גייסה 16 מיליון דולר כדי להפוך מכונות תעשיתיות לחכמות יותר - TheMarker","description":"החברה פיתחה תוכנה שמנתחת את המידע שמתקבל ממכונות בפסי הייצור ומתריעה על תקלות אפשריות ■ בגיוס השתתפו הקרנות אינסייט, טרו ונצ'רס ומור וי.סי","url":"https://www.themarker.com/technation/.premium-1.10571186","urlToImage":"https://www.themarker.com/polopoly_fs/1.10571219.1643288073!/image/79596495.jpg_gen/derivatives/headline_1200x630/79596495.jpg","publishedAt":"2022-01-27T12:50:00Z","content":", , . \" \", . , . \r\n\" \", , \". \r\n-2019, (Vanti Analytics) . ...\r\n<ol><li></li></ol><ol><li></li></ol><ol></ol>"},{"source":{"id":null,"name":"Globes.co.il"},"author":"אבישי עובדיה","title":"כך ישנה web3.0 את הכלכלה ואת הטכנולוגיה - גלובס","description":"תוך עשור מאז שפרצה הטכנולוגיה הביזורית לחיינו, משתמשי האינטרנט עברו מצרכנים ליוצרי תוכן • למהפכה הזו יש שמות רבים וכולם מייצגים חלק בפאזל של הדור הבא של האינטרנט web3.0 • כתבה ראשונה בסדרה","url":"https://www.globes.co.il/news/article.aspx?did=1001399920","urlToImage":"https://res.cloudinary.com/globes/image/upload/t_desktop_article_content_header_800*392/v1643281274/COT_Pic/64_a0uy4b.jpg","publishedAt":"2022-01-27T12:26:03Z","content":"'\r\n. , NFT, ' , , . .\r\n- , . , , , .\r\n - ’, , NFT . , -Web 3.0. , . . -90. : (web 1.0) - , (web 2.0) - , , - , .\r\n : \r\n , . , 1991, , , HTTP . , , . AOL, -MSN, -. .\r\n: \r\n Web 2.0. - , , , . . . , , ,… [+202 chars]"},{"source":{"id":null,"name":"Geektime.co.il"},"author":"עידן בן טובים","title":"אחד מהגיוסים הגדולים בתולדות ההייטק: Fireblocks גייסה 550 מיליון דולר ושווה כבר 8 מיליארד דולר - גיקטיים","description":"זו Fireblocks - חברה אחת, שגייסה יותר ממיליארד דולר - בפחות משנה אחת","url":"https://www.geektime.co.il/fireblocks-raises-550m-series-e/","urlToImage":"https://files.geektime.co.il/wp-content/uploads/2022/01/Fireblocks-team-1643277931-600x315.jpg","publishedAt":"2022-01-27T12:20:00Z","content":"Fireblocks – , – \r\n: , , Solana. : Fireblocks\r\n, Fireblocks () – . E 550 – 8 .\r\n - CapitalG ( ), D1 Capital Partners Spark ,Capital, General Atlantic, Index Ventures, Mammoth, Altimeter, Iconiq Strat… [+535 chars]"},{"source":{"id":null,"name":"Themarker.com"},"author":"סוכנויות הידיעות","title":"מקדונלד'ס ניסתה להתבדח עם מאסק - ויצרה בטעות מטבעות קריפטו - TheMarker","description":"המיליארדר צייץ כי יאכל ארוחת ילדים בשידור חי אם מקדונלד'ס תתחיל לקבל דוג'קוין כאמצעי תשלום ■ במקדונלד'ס לא נשארו חייבים - והמציאו מטבעות שערכם זינק באלפי אחוזים","url":"https://www.themarker.com/wallstreet/.premium-1.10570925","urlToImage":"https://img.haarets.co.il/img/1.10571214/3794673665.jpg?precrop=2168,1257,x32,y32&height=698&width=1200","publishedAt":"2022-01-27T11:10:00Z","content":", , ' ' , . ' - . \r\n ' ' \" (grimacecoin)\". , ' ."},{"source":{"id":null,"name":"Themarker.com"},"author":"דורון טל","title":"עידכון תוכנה: למה yes ו-HOT לא יוכלו להמשיך לתת לכם לדלג על פרסומות - TheMarker","description":"ההכנסות מדמי מנוי של yes ו-HOT הצטמצמו ביותר מ־30% בתוך 5 שנים כשמיליוני ישראלים \"חתכו כבלים\" ועברו לשירותי סטרימינג. עכשיו הן התעשתו ומבינות שעליהן לשלם לגופי תוכן ולאפשר פרסומות כדי להתחרות, והרגולטור צריך להרשות להן לעשות זאת","url":"https://www.themarker.com/advertising/1.10570310","urlToImage":"https://www.themarker.com/polopoly_fs/1.10570396.1643286198!/image/2702198338.jpg_gen/derivatives/headline_1200x630/2702198338.jpg","publishedAt":"2022-01-27T10:04:00Z","content":", , , . TheMarker , HOT  .\r\n, \" \" \" \". . . \"\" ( , yes+, ). \r\nyes -HOT  -30% 5 , . . , . . ( ?). -VOD , .\r\n(Cord cutting) \" , . \"11\" -makoTV. \r\n\" VOD ( + ) -FAST ( , , ) , , . \"\", , . ? . \" .\r\n.HOT- \r… [+101 chars]"},{"source":{"id":null,"name":"Themarker.com"},"author":"סימי ספולטר","title":"היי-טקיסטים? יוזמה חדשה רוצה שתתרמו 1.8% מהמניות או מהאופציות שלכם - TheMarker","description":"מיזם חדש רוצה לרתום את עובדי ההיי־טק לתרום לקהילה ■ המיזם, שמכונה \"אחד.שמונה\", מבקש מעובדים בתעשיית ההיי־טק לתרום 1.8% מהרווחים שלהם או מהאופציות שלהם בחברה ■ לכל תורם תהיה אפשרות הצבעה בשאלה לאן ינותב הכסף","url":"https://www.themarker.com/technation/.premium-1.10570379","urlToImage":"https://www.themarker.com/polopoly_fs/1.10570446.1643274204!/image/1107319390.jpg_gen/derivatives/headline_1200x630/1107319390.jpg","publishedAt":"2022-01-27T09:47:00Z","content":": -25 -20 . , . , .\r\n\".\", 1.8% , . , ...\r\n<ol><li></li></ol><ol><li></li></ol><ol></ol>"},{"source":{"id":null,"name":"Geektime.co.il"},"author":"מערכת גיקטיים","title":"חושבים לעבור מפיתוח לדאטה סיינס? תוכנית הסבה חדשה תכשיר אתכם תוך 14 שבועות - גיקטיים","description":"תוכנית ההכשרה הייחודית של חברת הפינטק Pagaya מיועדת לבעלי ניסיון מעשי ותואר אקדמי, ותימשך 14 שבועות בשכר מלא. בסופם יוכלו המתאימים להשתלב כחוקרים בחברה. ההרשמה פתוחה","url":"https://www.geektime.co.il/data-science-program/","urlToImage":"https://files.geektime.co.il/wp-content/uploads/2021/12/3F2C6640-1-1640086043-600x315.jpg","publishedAt":"2022-01-27T09:36:39Z","content":"Pagaya , 14 . . \r\n(: )\r\n, . – , , .\r\n , . Pagaya (), , , . : .\r\n“PagayaPro Switch” -6 2022, 14 . , 9:30-18:30.\r\n hands-on (STEM) -90, . .\r\n, , , , , .  .\r\n Pagaya\r\nPagaya , . -700 .\r\n -160 . - , .\r\n“… [+41 chars]"},{"source":{"id":null,"name":"Themarker.com"},"author":"בלומברג","title":"לקבל תשלום באמצעות סריקה לאייפון: אפל תשיק שירות חדש לעסקים קטנים - TheMarker","description":"השירות יאפשר לעסקים קטנים לקבל כסף ישירות לאייפון, ללא צורך בהתקנת חומרה נוספת ■ הפיתוח מתבסס על טכנולוגיה של סטארט-אפ קנדי שאפל קנתה ב-2020","url":"https://www.themarker.com/wallstreet/.premium-1.10570181","urlToImage":"https://www.themarker.com/polopoly_fs/1.10570190.1643275373!/image/3425060609.jpg_gen/derivatives/headline_1200x630/3425060609.jpg","publishedAt":"2022-01-27T09:13:00Z","content":", .\r\n2020, -100 - Mobeewave, . -NFC .\r\n, , ( ), \". , ,...\r\n<ol><li></li></ol><ol><li></li></ol><ol></ol>"},{"source":{"id":null,"name":"Geektime.co.il"},"author":"עידן בן טובים","title":"אפל הוציאה ”מדריך” כדי שלא יעקבו אחריכם עם AirTag - גיקטיים","description":"מה קורה כשחברה שהופכת את הפרטיות לפיצ׳ר משחררת מוצר שיכול לעשות את ההפך מזה? כאב ראש למחלקת ה-PR ומדריך זריז","url":"https://www.geektime.co.il/apple-releases-updated-personal-safety-guide-because-of-airtag/","urlToImage":"https://files.geektime.co.il/wp-content/uploads/2021/05/20210506_111310-1620303996-600x315.jpg","publishedAt":"2022-01-27T09:03:34Z","content":"? -PR \r\n: \r\nAirTag, – , . ?\r\n , \r\n -AirTag , : ,   , , . ,   , .\r\n . -AirTag , – 29 . , 8-24 , , .\r\n, -iOS 15.2 . , , . – , .\r\n ?\r\n, , , . , AirTag ( ) , . .\r\n( / ), . . PDF, , , .\r\n: \r\n, , Find My ,… [+84 chars]"},{"source":{"id":null,"name":"Globes.co.il"},"author":"אסף גלעד","title":"אינטל מציגה: חוות השרתים שהצילו לה את הרבעון - גלובס","description":"למזלה של אינטל, היא החלה למכור ברבעון השלישי של השנה החולפת שבבים חדשים לניהול תשתית התקשורת והענן, לאחר שסבלה שנים מפיגור בתחום • הדוחות לרבעון האחרון של השנה מראים כי העלייה על עגלת הענן, גם אם באיחור, השתלמה","url":"https://www.globes.co.il/news/article.aspx?did=1001400163","urlToImage":"https://res.cloudinary.com/globes/image/upload/t_desktop_article_content_header_800*392/v1629641121/direct/%D7%A4%D7%98_%D7%92%D7%9C%D7%A1%D7%99%D7%A0%D7%92%D7%A8_%D7%9E%D7%A0%D7%9B%D7%9C_%D7%90%D7%99%D7%A0%D7%98%D7%9C_%D7%94%D7%A2%D7%95%D7%9C%D7%9E%D7%99%D7%AA_akhsjh.jpg","publishedAt":"2022-01-27T08:31:17Z","content":". , . : , : .\r\n - , - . - - .\r\n  . X86 , AMD - - .\r\n , , , IPU, -DPU -. (Xeon).\r\n , . , .\r\n (') , , : (IoT), -25.8 .\r\n 20% . 7% . , , 18%.\r\n , -2.7% .\r\n, - - , 1.4 , 7% .\r\n -19.5 (non-GAAP) 3% . 4.62… [+135 chars]"},{"source":{"id":null,"name":"Calcalist.co.il"},"author":null,"title":"הנפילה בשוק הקריפטו במקביל למניות מערערת את חלום המפלט - כלכליסט","description":"בימים האחרונים קורס שוק המניות, ולצדו החל לצלול גם שוק הקריפטו. אותם המטבעות שהיו אמורים לשמש מקלט למשקיעים בעתות של מצוקה פיננסית מסורתית, התגלו כתנודתיים בדיוק כמו השוק שמפניו הבטיחו להגן","url":"https://www.calcalist.co.il/market/article/syid4njct","urlToImage":"https://images1.calcalist.co.il/picserver3/crop_images/2021/12/23/rJe0Z3boY/rJe0Z3boY_81_0_1120_631_0_large.jpg","publishedAt":"2022-01-27T05:47:44Z","content":", . 50% 37 , , ' , . 100 . \r\n: ; ; . 2009 : , , . , , , . \r\n, . , , , , . , , . , . , , .\r\n, , . , . , . . , , ; , ; , .\r\n, . , . 2020, , . , , . , . , , , .\r\nwindow._taboola = window._taboola || [];… [+31 chars]"},{"source":{"id":null,"name":"Themarker.com"},"author":"בלומברג","title":"הנשק החדש של סין נגד עמק הסיליקון: 10,000 סטארט־אפים בתחומים הכי חמים - TheMarker","description":"\"הענקים הקטנים\", סטארט־אפים המפתחים טכנולוגיה אסטרטגית, נחשבים על ידי השלטון בסין לנשק במלחמת הטכנולוגיה נגד ארה\"ב ■ במסגרת תוכנית הענקים, מקבלים הסטארט־אפים מהממשלה כסף, סיוע וחותמת כשרות ■ \"נבחרות חברות הכפופות למדיניות של סין\"","url":"https://www.themarker.com/wallstreet/.premium-1.10568540","urlToImage":"https://www.themarker.com/polopoly_fs/1.10568539.1643211822!/image/1147807444.jpg_gen/derivatives/headline_1200x630/1147807444.jpg","publishedAt":"2022-01-27T04:25:00Z","content":", , \" \" , .\r\n, , , , , .\r\nUisee, , \" \" . , ', . ...\r\n<ol><li></li></ol><ol><li></li></ol><ol></ol>"},{"source":{"id":null,"name":"Themarker.com"},"author":"עמרי זרחוביץ'","title":"המניות ששרדו את הנפילות, ואיך צ'ק פוינט שוב החברה הישראלית הכי גדולה - TheMarker","description":"הירידות בוול סטריט פגעו במניות הטכנולוגיה שאיבדו בתקופה האחרונה עשרות אחוזים משוויין ■ ארבע חברות — צ'ק פוינט, נייס, סולאראדג' וסנטינל וואן — נשארו בשווי של יותר מ–10 מיליארד דולר, ויש גם מניות שרושמות תשואה שנתית חיובית","url":"https://www.themarker.com/markets/.premium-1.10568960","urlToImage":"https://www.themarker.com/polopoly_fs/1.10568956.1643227926!/image/1159514241.jpg_gen/derivatives/headline_1200x630/1159514241.jpg","publishedAt":"2022-01-27T04:24:00Z","content":"\" , 20 \". , , , \" ' , .\r\n' , , 200 . . ' .\r\n...\r\n<ol><li></li></ol><ol><li></li></ol><ol></ol>"},{"source":{"id":null,"name":"Calcalist.co.il"},"author":null,"title":"בגלל הביקורת? קרן ביל ומלינדה גייטס הוסיפה 4 חברים למועצת הנאמנים שלה - כלכליסט","description":"המינויים החדשים יעלו את מספר החברים בהנהלת הקרן ל-6, כאשר ביל ומלינדה ימשיכו לכהן כיו\"רים משותפים של המועצה, המפקחת על תרומות בסכום של כ-50 מיליארד דולר. על המוסד הפילנתרופי נמתחה ביקורת שלנוכח השפעתו העצומה, יש צורך להרחיב את הנהגתו","url":"https://www.calcalist.co.il/world_news/article/b1d3ymkct","urlToImage":"https://images1.calcalist.co.il/picserver3/crop_images/2021/07/08/r1rocHEpd/r1rocHEpd_1_0_976_549_0_large.jpg","publishedAt":"2022-01-26T18:37:43Z","content":"\" , , (Strive Masiyiwa) . \r\n(Minouche Shafik), ' ' (Thomas J. Tierney), \" - Bridgespan Group - ( ' , ). \r\nwindow._taboola = window._taboola || [];\r\n _taboola.push({flush: true});"},{"source":{"id":"google-news","name":"Google News"},"author":null,"title":"המחשב שלכם מריץ Crysis? כדאי שתכינו אותו לקראת המשחק הבא - TGspot.co.il","description":null,"url":"https://news.google.com/__i/rss/rd/articles/CBMiPGh0dHBzOi8vd3d3LnRnc3BvdC5jby5pbC9jcnlzaXMtNC1pcy1jb21pbmctY3J5dGVrLWNvbmZpcm1zL9IBAA?oc=5","urlToImage":null,"publishedAt":"2022-01-26T17:58:11Z","content":null},{"source":{"id":null,"name":"Calcalist.co.il"},"author":"מאיר אורבך","title":"יוניקורן חדש נולד: פיירבולט גייסה 100 מיליון דולר לפי שווי של 1.4 מיליארד דולר - כלכליסט","description":"הסכום, שכולו ייכנס לקופת פיירבולט, גויס שנה אחרי השקת המוצר שפיתחה - מחסן נתונים בענן שמאפשר לנתח מידע בנפח גבוה. סכום הגיוסים של החברה שהקימו סער ביטנר ואלדד פרקש הגיע ל-269 מיליון דולר עד היום. בנוסף, פיירבולט, שלה 200 עובדים, מכריזה על גיוסו של CTO חדש, מו…","url":"https://www.calcalist.co.il/calcalistech/article/h1ccikkay","urlToImage":"https://images1.calcalist.co.il/picserver3/crop_images/2021/06/24/1096437/1096437_0_0_3000_2250_0_x-large.jpg","publishedAt":"2022-01-26T17:08:51Z","content":"- (Firebolt) 100 1.4 , 12 . \r\n 269 . . -2018 . , CMO.\r\n,  Alkeon Capital Sozo Ventures, Glyn Capital, Zeev Ventures, Angular Ventures, Dawn Capital, Bessemer Venture Partners, K5 Global  -TLV Partner… [+127 chars]"},{"source":{"id":null,"name":"Haaretz.co.il"},"author":"קייד מץ, ניו יורק טיימס","title":"הבטיחו לנו מחשבים קוונטים ומכוניות מעופפות; למה אנחנו עדיין מחכים? - הארץ","description":"רכבת ההייפ של עמק הסיליקון שועטת אל העתיד כשהיא מתודלקת במיליארדי דולרים, חלומות ענק והמון אמונה; הבעיה היא שלפעמים נראה שהיא משאירה את המציאות הרחק מאחור","url":"https://www.haaretz.co.il/captain/net/.premium-1.10564310","urlToImage":"https://www.haaretz.co.il/polopoly_fs/1.10564343.1643215137!/image/2260270524.jpg_gen/derivatives/headline_1200x630/2260270524.jpg?wtm=1.10564343","publishedAt":"2022-01-26T16:32:00Z","content":"2019 \" \".\r\n. -20 -10,000 .\r\n, . . , , ...\r\n<ol><li></li></ol><ol><li></li></ol><ol></ol>"},{"source":{"id":null,"name":"Geektime.co.il"},"author":"כתב אורח","title":"למה האופציות והמניות שלכם שוות פחות עכשיו, ולמה אתם לא צריכים להתרגש מזה - גיקטיים","description":"חברות הייטק ישראליות נסחרות בחצי מהשווי שלהן. למה זה קרה והאם המסיבה הגיעה לסופה? אמ;לק: כנראה שלא","url":"https://www.geektime.co.il/not-a-bubble-option-stocks-tech-workers/","urlToImage":"https://files.geektime.co.il/wp-content/uploads/2022/01/hakan-nural-Zrw7A4KapcY-unsplash-1643212077-600x315.jpg","publishedAt":"2022-01-26T16:21:08Z","content":null},{"source":{"id":null,"name":"Ice.co.il"},"author":"מערכת ice","title":"וואטסאפ בשדרוג למערכת: כך יראה העדכון החדש - אייס","description":"וואטסאפ משפרת שוב כמה אלמנטים של ממשק המשתמש, על ידי הבאת כמה אנימציות חדשות. זהו עדכון הבטא השני שבו WhatsApp מציגה חדשות עבור ממשק המשתמש","url":"http://www.ice.co.il/digital-140/news/article/842020","urlToImage":"https://img.ice.co.il/giflib/news/11ice29112021.jpg","publishedAt":"2022-01-26T15:56:00Z","content":"( unsplash)\r\nWhatsApp UWP 2.2201.2 , 2.7, : . , ."},{"source":{"id":null,"name":"Calcalist.co.il"},"author":null,"title":"קבוצת BRM משקיעה 30 מיליון דולר במיזם הגראז' של לאומי - כלכליסט","description":"הגראז', שמשקיע מקים ומלווה סטארט-אפים בתחומי הפינטק, סייבר ובינה מלאכותית, הוקם לפני מספר חודשים על ידי יזמי ההייטק עומר נגר, איל רדלר ושי דן. לאומי פרטנרס מחזיקה ב-20% מהבעלות בגראז'; קרן BRM צפויה לגייס ממשקיעים נוספים עד לסכום כולל של 160 מיליון דולר","url":"https://www.calcalist.co.il/calcalistech/article/skl0j11rf","urlToImage":"https://images1.calcalist.co.il/picserver3/crop_images/2021/11/14/1141471/1141471_36_0_569_320_0_large.jpg","publishedAt":"2022-01-26T15:23:37Z","content":"BRM \"'\" (\"The Garage\"), , - , , -AI. -30 . \r\nwindow._taboola = window._taboola || [];\r\n _taboola.push({flush: true});"},{"source":{"id":null,"name":"Gadgety.co.il"},"author":"https://www.facebook.com/ronen82","title":"שיאומי משיקה את ה-Redmi Note 11 בישראל החל ממחיר 900 ש”ח - Gadgety | גאדג'טי","description":"שעות בודדות לאחר ההכרזה הרשמית מגיעה גם ההשקה של מכשיר ה-Redmi Note 11 בישראל. הדגם החדש זמין לרכישה בארץ כבר מעכשיו, והוא מגיע בצבעים אפור וכחול ובגרסאות של 4 או 6 גיגה-בייט של זיכרון ו-128 גיגה-בייט של אחסון, החל ממחיר של 900 ש”ח. המכשיר מציע מסך AMOLED בגו…","url":"https://www.gadgety.co.il/286660/redmi-note-11-israel/","urlToImage":"https://www.gadgety.co.il/wp-content/themes/main/thumbs/2022/01/redmi-note-11-global-main.jpg","publishedAt":"2022-01-26T15:01:32Z","content":"-Redmi Note 11 . , 4 6 - -128 - , 900 ”.\r\n AMOLED 6.43 , +Full HD 90 , 13 -. , -4 , 50 -, 8 - 120 2 - .\r\n  Snapdragon 680 , 8 2.4 - 4G , nanoSIM . (RAM) 4 6 -, 128 - 1TB microSD, 5,000mAh 33 USB-C.\r\n… [+109 chars]"},{"source":{"id":"ynet","name":"Ynet"},"author":"אושרית גן-אל","title":"גוגל Topics: תחליף חדש לקוקיז - ynet.co.il","description":"ענקית הטכנולוגיה הציגה בשנה שעברה את מערכת FLoC, שהייתה אמורה להחליף עד 2023 את העוגיות שאוספות מידע על משתמשים, אך התעשייה הפנתה לה כתף קרה. כעת החברה מנסה את מזלה שוב עם מערכת Topics שאמורה לאפשר להציג פרסום מותאם אישית בלי לפגוע בפרטיות","url":"https://www.ynet.co.il/digital/technews/article/hjd5jar6y","urlToImage":"https://ynet-images1.yit.co.il/picserver5/crop_images/2021/04/22/SyT11V9C8O/SyT11V9C8O_0_0_1000_563_0_large.jpg","publishedAt":"2022-01-26T14:20:43Z","content":"-FLoC, \"\" () . ( ') Topics.\r\nFLoC . , , . , , , ', -Brave . \r\n350 - \" \", \"\", \"\", \"\" \"\". , - , . , ."},{"source":{"id":null,"name":"Globes.co.il"},"author":"שירי חביב ולדהורן","title":"טאבולה משיקה טכנולוגיה שתסייע לאתרי התוכן בקרב על הגולשים - גלובס","description":"חברת המלצות התוכן, שמנייתה נחתכה ב-50% מכניסתה לנאסד\"ק, תאפשר  התאמה אישית של תכנים חדשותיים בעמודי הבית של האתרים • המנכ\"ל אדם סינגולדה: \"בטווח הקצר זה 'באסה' שהשוק לא טוב, אבל יש חברות שלא תלויות בגיוס כספים אלא בעצמן\"","url":"https://www.globes.co.il/news/article.aspx?did=1001400050","urlToImage":"https://res.cloudinary.com/globes/image/upload/t_desktop_article_content_header_800*392/v1611739803/direct/1317938_yfif8x.jpg","publishedAt":"2022-01-26T13:12:48Z","content":", , - \" \".\r\n , , (AI), , . , Homepage For You, , . , 30%-50% .\r\n \" SPAC, 2.6 . -SPAC , . -SPAC , -50% -1.3 .\r\n AI \r\n , \" : \"-30 , '. , \". , , ' , AI , '. , .\r\n , , -AI . \" - engaged\", . \" '' '\".\r\n : … [+217 chars]"},{"source":{"id":null,"name":"Themarker.com"},"author":"סימי ספולטר","title":"\"מחשב יכול להחליף אותך\": הסטארט-אפ שהתחיל בוויכוח מגייס עוד 20 מיליון דולר - TheMarker","description":"הסטארט-אפ DigitalOwl מציע לחברות הביטוח לשפר את המהירות והיעילות של ניתוח מסמכים רפואיים, באמצעות בינה מלאכותית ■ בחברה שואפים ללמוד גם להמליץ לחברות על רמת הסיכון שיש לייחס לכל מבוטח","url":"https://www.themarker.com/technation/.premium-1.10561553","urlToImage":"https://www.themarker.com/polopoly_fs/1.10561677.1643198049!/image/2331962035.jpg_gen/derivatives/headline_1200x630/2331962035.jpg","publishedAt":"2022-01-26T13:00:00Z","content":"- , ? , - .\r\n\" \", , . \" , , . \". \r\n-2018 '- (DigitalOwl) , ...\r\n<ol><li></li></ol><ol><li></li></ol><ol></ol>"},{"source":{"id":null,"name":"Globes.co.il"},"author":"אתי אפללו","title":"מכשיר שני של אג\"ח מגובה קריפטו עומד להיכנס לשוק. איך הוא יעבוד? - גלובס","description":"קבוצת הנוסטרו אופורטו מצטרפת למהלך של סילבר קסטל, ומקדמת את הנפקת קריפטוניה - איגרת בשווי 100 מיליון דולר שתיסחר ברצף המוסדיים של הבורסה בתל אביב (TASE UP) • למי זה מתאים ומה חייבים לקחת בחשבון בהשקעה","url":"https://www.globes.co.il/news/article.aspx?did=1001399918","urlToImage":"https://res.cloudinary.com/globes/image/upload/t_desktop_article_content_header_800*392/v1643186740/COT_Pic/64_jey3fj.jpg","publishedAt":"2022-01-26T12:51:06Z","content":", . , , :  \" .\r\n\" (TASE UP). , 100 , .\r\n ? , . , . , , , . , , \". \" , .\r\n 0.9% (0.9% , 0.1% , 0.24% , 0.25% -0.1% , ),     1.4%. \" , - 2%, 1.5%.\r\n, . , ( : 8 , 1.2 1.8 , 5 , 600 900 ) .\r\n , , , , . ,… [+142 chars]"},{"source":{"id":"ynet","name":"Ynet"},"author":"רועי האן","title":"אין חגיגה בלי חוגה: בדקנו את הלפטופ החדש של אסוס - ynet.co.il","description":"מסך OLED מרשים, 64 גיגה-בייט זיכרון עבודה, מעבד אינטל מתקדם, כרטיס מסך ייעודי ליוצרי תוכן ו... חוגה? בדקנו את Studiobook 16 OLED, הלפטופ מבית Asus שמיועד ליוצרי תוכן ומתחיל במחיר של 12.3 אלף שקלים","url":"https://www.ynet.co.il/digital/reviews/article/syfuhxn6y","urlToImage":"https://ynet-images1.yit.co.il/picserver5/crop_images/2022/01/24/HyMxpl36F/HyMxpl36F_0_143_800_451_0_large.jpg","publishedAt":"2022-01-26T11:56:59Z","content":"-Studiobook 16 OLED : , . , . \r\nProArt 2019, . , , , . -Studiobook 16 OLED . ' - , . ? .\r\n16 ' 4K (3840x2400 ) OLED 60 16:10. - -HDR, 100% DCI-P3, PANTONE, 550 ( -617 ), SGS , -1.07 1,000,000:1. , . … [+356 chars]"},{"source":{"id":null,"name":"Walla.co.il"},"author":"צלי גרינברג","title":"האם בקרוב יוטל מס על הביטקוין? - וואלה! כסף","description":"בעוד רבים מנסים להבין מהו מטבע קריפטו, מקבל התחום את האישור על מרכזיותו בכלכלה העולמית, בדמות תכנון של רשויות המס בארהב למסות את הרווחים מהכסף הוירטואלי","url":"https://finance.walla.co.il/item/3485161","urlToImage":"https://images.wcdn.co.il/f_auto,q_auto,w_1200,t_54/3/1/2/2/3122462-46.jpg","publishedAt":"2022-01-26T11:33:00Z","content":"\" , 2 2017 -38 , 2021 -95 , 57 . 25% , 14.25 , -44,175 -3.1 .\r\n-4 , -10% . \r\n-3.5 , 133 . -294.5 . \r\n, 161.5 , 40.3 , -44.2 .\r\n, . , , \". \""},{"source":{"id":null,"name":"Themarker.com"},"author":"גרדיאן","title":"סמנו ביומנים: טיל של ספייס-אקס יצא משליטה - וצפוי להתנגש בירח - TheMarker","description":"מדעני חלל סבורים שהטיל נמצא במסלול להתנגשות בירח במהירות של 2.58 ק\"מ לשנייה בתוך שבועות ■ מתכנת תוכנות מעקב אחרי עצמים שמימיים: \"הטיל ייפגע בצד הרחוק של הירח, סמוך לקו המשווה, ב-4 במארס. זו הפעם הראשונה שפסולת חלל תפגע בירח\"","url":"https://www.themarker.com/wallstreet/.premium-1.10567313","urlToImage":"https://www.themarker.com/polopoly_fs/1.6407707.1534922971!/image/870512794.jpg_gen/derivatives/headline_1200x630/870512794.jpg","publishedAt":"2022-01-26T10:34:00Z","content":"- (SpaceX), , , - .\r\n- TheMarker ( - , )\r\n, 9, 2015 - . \" (NOAA) ' - - . \r\n, ...\r\n<ol><li></li></ol><ol><li></li></ol><ol></ol>"},{"source":{"id":null,"name":"Calcalist.co.il"},"author":null,"title":"\"כדי להתקדם לשלב הבא, חברה צריכה כישורים שלומדים בעולם האמיתי, לא ב-8200\" - כלכליסט","description":"כך אמר אמיתי רצון, מייסד ומנכ\"ל יוניקורן הסייבר הישראלי פנטרה, בכנס הסייבר של כלכליסט: \"לדעת איך לוקחים את החברה ממוצר מגניב שעושה משהו אמיתי לעולם הגדול - זה לא קשור לצבא, אלא לניסיון של עבודה בשוחות ובעולם האמיתי\"","url":"https://www.calcalist.co.il/conferences/article/h1ovnhppy","urlToImage":"https://images1.calcalist.co.il/picserver3/crop_images/2022/01/25/B1jgqzHST6K/B1jgqzHST6K_528_0_1390_783_0_large.jpg","publishedAt":"2022-01-26T10:31:56Z","content":"\", , , -8200\" , \" (Pentera), . \r\n, -8200 , . \" 8200 \", . \" , . . . , \" . , \".\r\n: \" : . . , . , : , . -2022\".\r\n\" . . , - . ' 10 -15 . . , , . \". \r\nwindow._taboola = window._taboola || [];\r\n _taboola.p… [+18 chars]"},{"source":{"id":null,"name":"Calcalist.co.il"},"author":null,"title":"חקיקה עכשיו: לא עד כדי כך מסובך לאזן בין חופש הפרט לצורך של המשטרה בפגסוס - כלכליסט","description":"כל מה שצריך לעשות כדי למנוע הישנות של מקרים כמו אלה המתוארים בתחקירי \"כלכליסט\" על שימושי המשטרה בתוכנת הריגול של NSO זה קופי-פייסט מדמוקרטיות מתקדמות כמו בריטניה וגרמניה. וזה בדיוק מה שהמכון הישראלי לדמוקרטיה בוחן כעת","url":"https://www.calcalist.co.il/calcalistech/article/r14dg9atk","urlToImage":"https://images1.calcalist.co.il/picserver3/crop_images/2020/01/21/963263/963263_0_150_1200_676_0_large.jpg","publishedAt":"2022-01-26T09:55:46Z","content":"( , ) ? : , . , (Investigatory Powers Act) : , , . (), : (BKAG). (StPO).\r\n? , . , \" \" (, ) . . ( \") . , .\r\n\" \" \" \", ( , , , , ). . . .\r\n\", : , , \", \"\" \". \" , , . , , , . , .\r\n. , , . , (IPCO) ( ) ( )… [+142 chars]"},{"source":{"id":null,"name":"Walla.co.il"},"author":"מערכת וואלה","title":"לוחמה בשטח בנוי: יוצאי היחידות הקרביות שכן הגיעו להייטק - וואלה! כסף","description":"המערכון מארץ נהדרת הבליט שוב את הטענה לפיה יוצאי יחידות קרביות מתקשים להיקלט בחברות הייטק. אנחנו מצאנו כמה דמויות מעוררות השראה שעשו את זה בגדול","url":"https://finance.walla.co.il/item/3484835","urlToImage":"https://images.wcdn.co.il/f_auto,q_auto,w_1200,t_54/3/3/3/8/3338659-46.jpg","publishedAt":"2022-01-26T09:52:00Z","content":": \" , \" '\r\n, 45 + 3 , - COO 2 Automat-IT - DevOps . , , 31 , \". - 2006 . \r\n\" \", , \" , 31, - 8200. , , . . \" 77 , , . \r\n\" ' , . 5,000 \". \r\n, , \" , - . \" IT, End User Support, . . . !. . . , , . 30% , … [+142 chars]"},{"source":{"id":null,"name":"Mako.co.il"},"author":"דנה גוטרזון","title":"לקוח של פלאפון חויב על שירותים חינמיים של אפל - mako","description":"יואב גילה בחשבונית שלו כי במשך החודשים האחרונים הוא חויב על שירותים חינמיים של אפל כמו iMessage ו-FaceTime, וגילה כי הדבר קרה גם למשתמשים אחרים","url":"https://www.mako.co.il/nexter-news/Article-b2b9015cac59e71027.htm","urlToImage":"https://img.mako.co.il/2022/01/26/shutterstock_1879884001_autoOrient_i.jpg","publishedAt":"2022-01-26T09:50:00Z","content":"- iMessage -FaceTime – . , 1.99 .\r\n \"SMS \" 1 . \" \", -mako. \" (iMessage -FaceTime)\".\r\n , , .\r\n\" \", . \" . , \". - 35 , - -2 .\r\n() \" . , \"\".\r\n: \" , SIM SMS \" ( imassage -facetime), . . \".\r\n ?"},{"source":{"id":null,"name":"Globes.co.il"},"author":"אופיר דור","title":"שיחת המשקיעים של מיקרוסופט הצילה את המניה מהתרסקות - גלובס","description":"ענקית הטכנולוגיה דיווחה על הכנסות ורווח גבוהים מהמצופה, אך איכזבה בשורה החשובה ביותר - הצמיחה בהכנסות הענן • רק הסבר מאוחר של סמנכ\"לית הכספים הצליח להחזיר את מניית מיקרוסופט, כמו גם את מניות אמזון ואלפאבית, למגמה חיובית במסגרת המסחר המאוחר בארה\"ב","url":"https://www.globes.co.il/news/article.aspx?did=1001399981","urlToImage":"https://res.cloudinary.com/globes/image/upload/t_desktop_article_content_header_800*392/v1643188363/agencies-website/AP19225626820447_qqsjkz.jpg","publishedAt":"2022-01-26T09:20:23Z","content":"(') 2022, . , .\r\n -20% 51.7 . 50 . -21% -18.8 , . -5%?\r\n , .   () , , ' (Azure), , . , ' -46%, 59% 2020. ' 50%.\r\n , , ( ) , ' -69 , . , , 51% -2021, -27% S&amp;P 500. ' .\r\n. . - (AWS) ( ). 30% , -20%… [+68 chars]"},{"source":{"id":null,"name":"Bizportal.co.il"},"author":null,"title":"קרן המטבע מפצירה באל סלבדור לוותר על הביטקוין - Bizportal","description":"אל סלבדור בהנהגת הנשיא בוקלה היא המדינה הראשונה שמאמצת את הביטקוין כהילך חוקי, קרן המטבע העולמית חוששת מהיציבות הפיננסית ובטחון הצרכנים ומפצירה במדינה לחזור בה, זאת על רקע שיחות להלוואה של 1.3 מיליארד דולר שמבקשת המדינה מקרן המטבע","url":"https://www.bizportal.co.il/digital-currency/news/article/800595","urlToImage":"https://res.cloudinary.com/bizportal/image/upload/v1609665178/giflib/news/BITCON UP OR DOWN 10092021.PNG","publishedAt":"2022-01-26T09:19:00Z","content":"\" -8000 . 2019 , ( '), , . \r\n. , , . \r\n. 2021 , , . , , . -15 \" \".\r\n, . , Chivo . -70% , . 30 , .  \r\n. , , . \" , , \" . . \r\n\" . . , , . 1.3 . -96% 2026, ."},{"source":{"id":null,"name":"Calcalist.co.il"},"author":null,"title":"כך תשתנה חווית הקניות שלנו באינטרנט - כלכליסט","description":"היקף הקניות המקוונות נמצא בעלייה מתמדת - מה התפריט הנכון למסחר אלקטרוני מוצלח?","url":"https://www.calcalist.co.il/calcalistech/article/bjmvjya6f","urlToImage":"https://images1.calcalist.co.il/picserver3/crop_images/2016/11/25/667879/667879_0_0_580_330_0_large.jpg","publishedAt":"2022-01-26T08:32:31Z","content":"(25% , -30%-50% -2023) . . \r\nwindow._taboola = window._taboola || [];\r\n _taboola.push({flush: true});"},{"source":{"id":"ynet","name":"Ynet"},"author":"רועי האן","title":"מתי יוצא סמסונג גלקסי S22? כל הפרטים - ynet.co.il","description":"ב-9 בפברואר צפויה הענקית הקוריאנית לחשוף את סדרת מכשירי הדגל החדשה. איך ייראו הסמארטפונים החדשים, כמה הם יעלו לנו האם סדרת ה-S תתאחד עם סדרת הנוט?","url":"https://www.ynet.co.il/digital/mobile/article/sypm5wnaf","urlToImage":"https://ynet-images1.yit.co.il/picserver5/crop_images/2022/01/26/rJC11OdC6Y/rJC11OdC6Y_0_0_998_560_0_large.jpg","publishedAt":"2022-01-26T08:28:27Z","content":"- , . -S21, 6.06 ' 6.55 '. 120 +FHD. , , .\r\n, . 6.81 ' 120 +QHD. , , 20. , . , , .\r\n, , . , , -Exynos 2200, , -Snapdragon 8 Gen 1. , -8 - (RAM) 256 - 16 - ( -8 -) 512 - . 1 -.\r\n, 3,700 -, 4,500 - 5,0… [+57 chars]"},{"source":{"id":"ynet","name":"Ynet"},"author":"יובל מן","title":"דיווח: המטבע של מטא מתקרב לסוף דרכו - ynet.co.il","description":"אגודת דיאם, שהייתה אמורה להשיק מטבע קריפטוגרפי באותו שם, שוקלת למכור את נכסיה על מנת להחזיר למשקיעים חלק מהכסף - כך מדווח אתר בלומברג. היוזמה נתקלה בקשיים רגולטוריים מרגע ההכרזה עליה באמצע 2019","url":"https://www.ynet.co.il/digital/technews/article/ry8jr0006k","urlToImage":"https://ynet-images1.yit.co.il/picserver5/crop_images/2019/10/23/9553916/9553916_0_0_5935_3339_0_large.jpg","publishedAt":"2022-01-26T07:50:30Z","content":null},{"source":{"id":null,"name":"Calcalist.co.il"},"author":null,"title":"פעילות החברות בנות של NSO: יירוט רחפנים וחדירה לרשת IoT - כלכליסט","description":"הבקשה שהוגשה לבית המשפט נותנת הצצה לפעילות של קבוצת NSO הרחבה. ווייאאוט היא החשאית מביניהן ומייסדה הוא אחיה של הנשיאה","url":"https://www.calcalist.co.il/calcalistech/article/ryfvnpt6k","urlToImage":"https://images1.calcalist.co.il/picserver3/crop_images/2022/01/25/ByqzDha6t/ByqzDha6t_0_0_2000_1126_0_large.jpg","publishedAt":"2022-01-25T21:40:43Z","content":"', \" BRG Asset Management, : \" , . , . . NSO, . , - NSO . \".\r\nwindow._taboola = window._taboola || [];\r\n _taboola.push({flush: true});"},{"source":{"id":null,"name":"Themarker.com"},"author":"ניו יורק טיימס","title":"טירוף הסטארט־אפים בארה\"ב בשיאו: \"אף פעם לא ראיתי שוק תחרותי יותר\" - TheMarker","description":"המגפה העניקה אינספור הזדמנויות עסקיות לסטארט־אפים, ויצרה אקוסיסטם משגשג של חברות עשירות במזומן, ששוויין רק עולה ■ אזהרות מפני בועה לא איחרו להגיע, אך משקיעים בתחום טוענים כי אפילו אם תהיה האטה זמנית, התמונה תמשיך להיות מבטיחה","url":"https://www.themarker.com/wallstreet/.premium-1.10565605","urlToImage":"https://www.themarker.com/polopoly_fs/1.10565604.1643136965!/image/2463767092.jpg_gen/derivatives/headline_1200x630/2463767092.jpg","publishedAt":"2022-01-25T19:08:00Z","content":"? , 900 . 2015 80 , . , . .\r\n\" 1,000 \", , , , . \" , \".\r\n, . ...\r\n<ol><li></li></ol><ol><li></li></ol><ol></ol>"},{"source":{"id":null,"name":"Bizportal.co.il"},"author":null,"title":"מנכ\"ל אמריקן אקספרס: \"איך אפשר לקרוא לביטקוין מטבע? הוא מתרסק\" - Bizportal","description":"סטיבן סקורי, מנכ\"ל ויו\"ר ענקית התשלומים מצדיק את גישתו השמרנית כלפי המטבעות: \"אי אפשר להתעלם ממה שקורה עם הביטקוין, הוא יורד ב-50% תוך חודשיים, אמריקן אקספרס לא צריכה להשתכשך עדיין במים הלא ידועים של הקריפטו\"","url":"https://www.bizportal.co.il/globalmarkets/news/article/800542","urlToImage":"https://res.cloudinary.com/bizportal/image/upload/v1609665178/giflib/news/BITCOIN22222.PNG","publishedAt":"2022-01-25T18:39:00Z","content":", \" \"   \r\nAMERICAN EXPRESS+8.93%AMERICAN173.13+8.93%:0:165.42:174.47:160:-- : , . \" . \r\nBITCOIN-0.36%BITCOIN36,692.31-0.36%:36,826.34:0:37,552.3:35,722.43:-- : - -50% . ?\" .\r\n. 36,858 , 23% . ' 46% -… [+192 chars]"},{"source":{"id":null,"name":"Geektime.co.il"},"author":"יניב אביטל","title":"סטארטאפ הגיימינג הישראלי Overwolf משקיע בסטארטאפ הגיימינג הישראלי Kidas - גיקטיים","description":"הסטארטאפ הישראלי Overwolf, שפיתח פלטפורמה ליצירת תוכן ומוניטיזציה במשחקים ומודים השקיע בסטארטאפ Kidas, שמסנן תכנים פוגעניים לילדים במשחקי רשת","url":"https://www.geektime.co.il/israeli-gaming-startup-overwolf-invests-in-israeli-gaming-startup-kidas/","urlToImage":"https://files.geektime.co.il/wp-content/uploads/2022/01/ralston-smith-zc9pWsPZd4Y-unsplash-1643131267-600x315.jpg","publishedAt":"2022-01-25T18:07:20Z","content":"Overwolf, Kidas, \r\n: Unsplash\r\n, . , -Kidas – .\r\nProtectMe Kidas, . , ProtectMe ’ , , . , , . , , , .\r\n , , PC.\r\nKidas -2019 Pitchbook -2 Comcast NBCUniversal LIFT Labs Techstars; Contour Venture Par… [+241 chars]"},{"source":{"id":null,"name":"Ice.co.il"},"author":"יאיר מור","title":"מיקרוסופט באזהרה חמורה למאות מיליוני משתמשים - אייס - אייס","description":"האקרים מצאו שיטה חדשה לפרוץ למשתמשים בשירות המייל השני בגודלו בעולם אחרי ג'ימייל. איך ההאקרים עושים את זה וממה צריך להיזהר?","url":"http://www.ice.co.il/digital-140/news/article/841934","urlToImage":"https://img.ice.co.il/giflib/news/16ice19122021.jpg","publishedAt":"2022-01-25T17:46:00Z","content":"( pixabay)\r\n, OAuth, , . , . : , , , , .\r\n\" ( ) Azure AD \", , , , ."},{"source":{"id":null,"name":"Hwzone.co.il"},"author":"יונתן מנדלסון","title":"מחשבים ניידים מבית אסוס במחירים נמוכים במיוחד, עכשיו באמאזון • HWzone - HWzone","description":"בואו להתחדש במחשבים היברידיים או במחשבים עם מסכים משניים בתמורה למחירים שלא תמצאו בשום מקום אחר","url":"https://hwzone.co.il/main-computers/%d7%9e%d7%97%d7%a9%d7%91%d7%99%d7%9d-%d7%a0%d7%99%d7%99%d7%93%d7%99%d7%9d-%d7%9e%d7%91%d7%99%d7%aa-%d7%90%d7%a1%d7%95%d7%a1-%d7%91%d7%9e%d7%97%d7%99%d7%a8%d7%99%d7%9d-%d7%a0%d7%9e%d7%95%d7%9b%d7%99/","urlToImage":"https://hwzone.co.il/wp-content/uploads/2022/01/reek8041.jpg","publishedAt":"2022-01-25T16:26:26Z","content":"Western Digital – ( ) , . , !\r\n VivoBook 15 ' IPS 1080p, Core i3-1115G4 -Tiger Lake , DDR4 8GB, NVMe 128GB, Wi-Fi 6 , 37 - 11 S-Mode ( Home ) 404.99 , -479.07 \", 1,526 -1,563 .\r\n -Amazon\r\nVivoBook Fl… [+210 chars]"},{"source":{"id":null,"name":"Gadgety.co.il"},"author":"https://www.facebook.com/ian.langerman.3","title":"הדלפה חדשה מספקת מבט מקרוב לטאבלט ה-Galaxy Tab S8 - Gadgety | גאדג'טי","description":"הדלפה חדשה המגיעה מהמדליף המוכר אוון בלאס (evleaks@) נותנת לנו הצצה נוספת על טאבלט ה-Galaxy Tab S8 של סמסונג, שהכרזתו הרשמית צפוי להגיע בעוד כשבועיים לצד סדרת ה-Galaxy S22 כחלק מאירוע ה-Galaxy Unpacked הקרוב של החברה, כדגם הבסיסי במשפחת ה-Tab S8 שישלב מסך בגו…","url":"https://www.gadgety.co.il/286566/galaxy-tab-s8-design-leak/","urlToImage":"https://www.gadgety.co.il/wp-content/themes/main/thumbs/2022/01/Samsung-Galaxy-Tab-S8-Black.webp","publishedAt":"2022-01-25T14:13:11Z","content":"(evleaks@) -Galaxy Tab S8 , -Galaxy S22 -Galaxy Unpacked , -Tab S8 11 ’.\r\n , -Galaxy Unpacked 2022, , -9 , Galaxy S22, Galaxy Tab S8 -Galaxy Tab S7.\r\n -Tab S8, -Tab S8 Plus -Tab S8 Ultra, 11, 12.4 -1… [+335 chars]"},{"source":{"id":null,"name":"Themarker.com"},"author":"רם בן ישי","title":"ירידות שווי בשוק הסטארט-אפים? 7 סיבות לכך שזה לא עומד לקרות - TheMarker","description":"שווי חברות הטכנולוגיה הציבוריות התרסק, ורבים שואלים את עצמם מה תהיה ההשפעה על השוק הפרטי ■ התחרות בתעשיית ההון סיכון והשינויים שביצעו הסטארט-אפים הם רק חלק מהסיבות לכך שלא צריך להיכנס לפאניקה","url":"https://www.themarker.com/technation/.premium-1.10564641","urlToImage":"https://www.themarker.com/polopoly_fs/1.10564731.1643118902!/image/3209783192.jpg_gen/derivatives/headline_1200x630/3209783192.jpg","publishedAt":"2022-01-25T13:47:00Z","content":", . -2021 - . 399 142.5 : - 45% 14 2022, Renaissance Capital. 15% .\r\n\"\" , \"\" . - ...\r\n<ol><li></li></ol><ol><li></li></ol><ol></ol>"},{"source":{"id":null,"name":"Calcalist.co.il"},"author":null,"title":"דיווח: Nvidia זונחת את המיזוג של 40 מיליארד דולר עם Arm - כלכליסט","description":"לפי הדיווח בבלומברג, אנבידיה עומדת לסגת מהמיזוג המתוכנן לנוכח לנוכח ההבנה שהסיכוי לאישור רגולטורי של העסקה בארה\"ב ובבריטניה הוא קלוש","url":"https://www.calcalist.co.il/calcalistech/article/skk11m006ak","urlToImage":"https://images1.calcalist.co.il/picserver3/crop_images/2021/04/19/S1PE411oLd/S1PE411oLd_119_50_906_510_0_large.jpg","publishedAt":"2022-01-25T13:39:51Z","content":"window._taboola = window._taboola || [];\r\n _taboola.push({flush: true});"},{"source":{"id":"ynet","name":"Ynet"},"author":"בשיתוף רשת מכללות עתיד","title":"הכירו את המקצוע שמניע את גלגלי המשק - ynet.co.il","description":"בשנה האחרונה חל גידול של 21% במספר המשרות הפנויות בסקטור ההנדסאים, כמו גם גידול של ארבעה אחוזים במספר התלמידים במכללות הטכנולוגיות. \"יותר ויותר צעירים מבינים שהטכנולוגיה משנה את שוק העבודה\", אומר אייל קרמר, מנכ\"ל רשת מכללות עתיד וקבוצת עתיד","url":"https://www.ynet.co.il/economy/article/rjmvjx2ty","urlToImage":"https://ynet-images1.yit.co.il/picserver5/crop_images/2019/08/26/9443923/9443923_85_0_896_504_0_large.jpg","publishedAt":"2022-01-25T13:38:24Z","content":"21% - 2021 2019. \" \" . , , , . , , , , . .\r\n\" \" 2020. \" 95% - 90% - 88%. : ."},{"source":{"id":null,"name":"Calcalist.co.il"},"author":null,"title":"אופטימיות זהירה: מחירי כרטיסי המסך מתחילים לרדת - כלכליסט","description":"ברשתות קמעונות ובאתר איביי, נרשמה ירידה של 5%-10% במחירי ה-GPU בחודש ינואר. מחירי המעבדים הגרפיים שברו שיאים בשנתיים האחרונות, על רקע המחסור העולמי בשבבים, הביקוש המוגבר למחשבי גיימינג והצורך בכרטיסי מסך חזקים לכריית מטבעות קריפטו","url":"https://www.calcalist.co.il/calcalistech/article/rjikwot6y","urlToImage":"https://images1.calcalist.co.il/picserver3/crop_images/2022/01/25/HyBRG00pTK/HyBRG00pTK_165_176_2655_1495_0_large.jpg","publishedAt":"2022-01-25T12:55:52Z","content":", -RTX 3080 (Nvidia) 1,773 - . , -1,600 . -RTX 30 -Radeon RX 6000 AMD , 5% -10%. -RX 6900 XT AMD.\r\n. GPU , . \"\", , , -3060 -3070. -3080 -3090 .\r\nTom's Hardware . . -GPU , . , -GPU .\r\nwindow._taboola … [+55 chars]"},{"source":{"id":"ynet","name":"Ynet"},"author":"רועי האן","title":"נוזקה חדשה ומתוחכמת מדאיגה את עולם הסייבר - ynet.co.il","description":"הנוזקה MoonBounce מסוגלת להתחבא בתוך שבב ה-BIOS של המחשב ובכך להמשיך לאיים על המערכת גם לאחר שעברה פרמוט. מומחי סייבר מעריכים כי קבוצת האקרים סינית עומדת מאחוריה","url":"https://www.ynet.co.il/digital/technews/article/ry8apht6t","urlToImage":"https://ynet-images1.yit.co.il/picserver5/crop_images/2021/08/10/Hy11zEZeeY/Hy11zEZeeY_0_0_1000_563_0_large.jpg","publishedAt":"2022-01-25T10:34:24Z","content":". , 2019 \" , LoJax -MosaicRegressor. , , MoonBounce \" \", . \r\nMoonBounce, . , , . , , , .\r\n? -BIOS . BIOS , . ' BootGuard TMP ( Trust Platform Module), ."},{"source":{"id":null,"name":"Calcalist.co.il"},"author":null,"title":"ה-Airbnb של העננים: רידג' של גיגי לוי-וייס ומייסד אקמאי גייסה 12 מיליון דולר - כלכליסט","description":"הסטארט-אפ הישראלי מספק שירותי ענן לתשתיות קיימות בדאטה סנטרים ברחבי העולם. לוי-וייס: \"בעבר, פריסת ענן הייתה מוגבלת ותלויה בתשתיות אך כעת, הודות לרידג', המגבלה הזאת אינה קיימת עוד\"","url":"https://www.calcalist.co.il/calcalistech/article/h1msn4tat","urlToImage":"https://images1.calcalist.co.il/picserver3/crop_images/2020/05/12/990394/990394_0_0_1200_675_0_large.jpg","publishedAt":"2022-01-25T10:12:18Z","content":"' (Ridge) 12 2021. NFX - A Chartered Group. Mayfield, Slow Ventures -Viola. -2019 10 .\r\n' , \" , , \" -CTO, ' , \" . -, -NFX . Akamai -CDN. \r\n' . T-Systems, NTT -INAP. . -2019 -40 . \r\n\"' , - \", -. \", , … [+94 chars]"},{"source":{"id":null,"name":"Calcalist.co.il"},"author":null,"title":"שיעור הצמיחה של IBM ברבעון החולף היה הגבוה ביותר ב-11 השנים האחרונות - כלכליסט","description":"הכנסותיה של חברת התוכנה עלו ברבעון הרביעי של 2021 ב-6% ועמדו על 16.7 מיליארד דולר. גם הרווח המתואם היה גבוה מהתחזיות והרווח הנקי זינק ב-72%, בין השאר הודות למכירת חטיבת השירותים לתשתיות קינדריל. המנכ\"ל ארווינד קרישנה רומז לרכישות עתידיות","url":"https://www.calcalist.co.il/calcalistech/article/ryixcet6k","urlToImage":"https://images1.calcalist.co.il/picserver3/crop_images/2021/05/06/1080800/1080800_0_30_680_383_0_large.jpg","publishedAt":"2022-01-25T10:02:17Z","content":"IBM -6% , (') . -IBM 3.35 , 3.30 . 16.7 15.96 . \r\n(Kyndryl), 4.6 . 2% . 2011. -72% , -2.33 , -56.9% -58.9%. \r\n\" IBM 5% 10-10.5 -2022. \" ' . \"\". \" , \", . \" - \". \r\n, 7.27 , 8% -6.72 . , -13% -4.75 , -4… [+136 chars]"},{"source":{"id":null,"name":"Gadgety.co.il"},"author":"https://www.facebook.com/profile.php?id=100010175887752","title":"הדלפה: עיצובו של מכשיר הדגל Lenovo Halo נחשף עם מערכת השבבים Snapdragon 8 Gen 1 Plus - Gadgety | גאדג'טי","description":"בשעה שלנובו מחזיקה בבעלות על המותג הנוסטלגי והמוכר מוטורולה (Motorola) ממנו היא משחררת לא מעט סמארטפונים, החברה עדיין מחזיקה בלא מעט סמארטפונים הנושאים את השם הישיר שלה כדוגמת ה-Lenovo Legion Phone Duel 2. במכשירים האלה נראה שלנובו בוחרת להתמקד בנישת הגיימינג…","url":"https://www.gadgety.co.il/286538/lenovo-halo-design-leak/","urlToImage":"https://www.gadgety.co.il/wp-content/themes/main/thumbs/2022/01/Lenovo-Halo-Leak.jpg","publishedAt":"2022-01-25T09:45:30Z","content":"(Motorola) , -Lenovo Legion Phone Duel 2. , Lenovo Halo.\r\n , -Duel 2, . , -LED Legion .\r\n “50MP AI Triple Camera“, 50 . . 6.67 ’, +Full HD, POLED 144 300 .\r\nLenovo Halo (: evleaks)\r\nSM8475, Snapdrago… [+134 chars]"},{"source":{"id":null,"name":"Themarker.com"},"author":"יואב כהן","title":"\"כבר לא צריך להתארגן ולבוא לראיון, מראים את המשרד למועמד עם המצלמה\" - TheMarker","description":"מנהל גיוס והשמה בחברה אחראי על תהליכי איתור, גיוס, אבחון והשמה של עובדים ■ כמה מרוויחים בתפקיד, איך הקורונה שינתה אותו - ומה אפשר לעשות כדי להגיע אליו?","url":"https://www.themarker.com/career/.premium-1.10564176","urlToImage":"https://www.themarker.com/polopoly_fs/1.10564206.1643102556!/image/1946047366.jpg_gen/derivatives/headline_1200x630/1946047366.jpg","publishedAt":"2022-01-25T09:09:00Z","content":"\" \" , , . \" . '. , . , \".\r\n, , ...\r\n<ol><li></li></ol><ol><li></li></ol><ol></ol>"},{"source":{"id":null,"name":"Themarker.com"},"author":"יואב כהן","title":"\"כבר לא צריך להתארגן ולבוא לראיון, מראים את המשרד למועמד עם המצלמה\" - TheMarker","description":"מנהל גיוס והשמה בחברה אחראי על תהליכי איתור, גיוס, אבחון והשמה של עובדים ■ כמה מרוויחים בתפקיד, איך הקורונה שינתה אותו - ומה אפשר לעשות כדי להגיע אליו?","url":"https://www.themarker.com/career/.premium.HIGHLIGHT-1.10564176","urlToImage":"https://www.themarker.com/polopoly_fs/1.10564206.1643102556!/image/1946047366.jpg_gen/derivatives/headline_1200x630/1946047366.jpg","publishedAt":"2022-01-25T09:09:00Z","content":"\" \" , , . \" . '. , . , \".\r\n, , ...\r\n<ol><li></li></ol><ol><li></li></ol><ol></ol>"},{"source":{"id":null,"name":"Maariv.co.il"},"author":"סוכנויות הידיעות","title":"\"היכן שכביש פוגש שמים\": מכונית מעופפת קיבלה אישור שימוש בסלובקיה - מעריב","description":"'AIRCAR' של חברת 'קליין ויז'ן', ביצעה מעל 70 שעות של בדיקות טיסה וכ-200 המראות ונחיתות, ותואם לתקנים של הסוכנות האירופית לבטיחות תעופה. מהחברה נמסר: \"צעד נוסף וחשוב לייצור המוני\"","url":"https://www.maariv.co.il/business/tech/Article-893561","urlToImage":"https://images.maariv.co.il/image/upload/f_auto,fl_lossy/c_fill,g_faces:center,h_407,w_690/698523","publishedAt":"2022-01-25T07:29:00Z","content":": () , 70 , , 200 .\r\n ' '' , : \"-'AirCar' BMW 1.6 , . . \".\r\n , : \" \". ' '' -2020, - .\r\n :\r\nLos autos voladores están más cerca que nunca 'AirCar' es un vehículo con motor #BMW de modo dual que puede … [+284 chars]"},{"source":{"id":null,"name":"Bizportal.co.il"},"author":null,"title":"הזדמנות בירידות? במגדל ממליצים על חברות טכנולוגיה ישראליות שצפיות לעלות ב-20% - Bizportal","description":"הרעידות בשווקים מייצרות גם הזדמנויות מעניינות - כך מעריך נועם מאירוביץ ממגדל שוקי הון שמסמן 3 חברות ישראליות שנסחרות גם כאן וגם מעבר לים עם אפסייד גבוה: סאפיינס, נובה ונייס - צפו בראיוןTV","url":"https://www.bizportal.co.il/capitalmarket/news/article/800427","urlToImage":"https://res.cloudinary.com/bizportal/image/upload/v1609665178/giflib/news/Top_Biz_Noam Myroviz_23_01_22.00_05_48_08.Still023.png","publishedAt":"2022-01-25T05:55:00Z","content":", , 3 . \" 3 : - \r\n+2.91%9,799+2.91%:9,522:9,684:9,803:9,633:598,876 : -25% 118 .\r\n+2.49%36,230+2.49%:35,350:36,490:36,570:36,000:5,028,373 :.  ' -20% 46 .\r\n  , \r\n+3.42%79,740+3.42%:77,100:79,680:80,0… [+39 chars]"},{"source":{"id":"ynet","name":"Ynet"},"author":"אושרית גן-אל","title":"אפל נקנסת במיליוני אירו בהולנד - ynet.co.il","description":"רגולטור התחרות ההולנדי קונס את ענקית הטכנולוגיה, לאחר שזו לא עמדה בהוראתו לאפשר מערכות תשלום אלטרנטיביות באפליקציות דייטינג באפסטור. הקנס עומד על 5 מיליון אירו, ויוטל בכל שבוע עד שאפל תשנה את מדיניותה","url":"https://www.ynet.co.il/digital/technews/article/sk2dwot6t","urlToImage":"https://ynet-images1.yit.co.il/picserver5/crop_images/2020/10/25/S1bauJsGdD/S1bauJsGdD_0_175_3000_1689_0_large.jpg","publishedAt":"2022-01-25T03:20:00Z","content":"-5 . , , , . , 15-30% , , - , . \r\n(ACM) , . -ACM -2019, . . ' , , . -15 .\r\n, , . , - \" \". -ACM , . \" \", -ACM. , 5 -50 , ."}]}